turingmarkov/__main__.py
turingmarkov/turing.py
turingmarkov/markov.py
turingmarkov/__init__.py
turingmarkov/tests/test_markov.py
turingmarkov/tests/test_main.py
turingmarkov/tests/__init__.py
turingmarkov/tests/test_turing.py
turingmarkov-0.1.4.dist-info/top_level.txt
turingmarkov-0.1.4.dist-info/RECORD
turingmarkov-0.1.4.dist-info/metadata.json
turingmarkov-0.1.4.dist-info/entry_points.txt
turingmarkov-0.1.4.dist-info/DESCRIPTION.rst
turingmarkov-0.1.4.dist-info/WHEEL
turingmarkov-0.1.4.dist-info/METADATA
