Metadata-Version: 2.0
Name: turingmarkov
Version: 0.1.4
Summary: Turing machine and markov algorithm emulator.
Requires-Dist: pytest
